.gitignore
.gitlab-ci.yml
CONTRIBUTING.rst
Dockerfile
LICENSE
MANIFEST.in
Makefile
Readme.rst
Singularity
requirements.txt
requirements_dev.txt
setup.py
.gitlab/issue_templates/Bug.md
.gitlab/issue_templates/Feature.md
configs/bundle_ORCA4_corsika_sibyll_2-3c.toml
configs/bundle_ORCA4_data_v5-40.toml
configs/bundle_ORCA4_mupage_v5-40.toml
configs/nu_chain_data_ORCA6.toml
configs/nu_chain_muon_ORCA6.toml
configs/nu_chain_neutrino_ORCA6.toml
docs/CONTRIBUTING.rst
docs/Makefile
docs/conf.py
docs/contributing_link.rst
docs/getting_started.rst
docs/index.rst
docs/orcasong.rst
docs/tools.rst
docs/_static/.gitkeep
docs/_static/orcasong.svg
docs/_static/orcasong_logo_small.png
docs/_static/orcasong_logo_small_low_res.png
docs/_static/orcasong_wide.png
docs/_static/orcasong_wide.svg
docs/_static/orcasong_wide_transparent.png
docs/_static/orcasong_wide_transparent.svg
docs/_static/orcasong_wide_transparent_white.png
docs/_static/orcasong_wide_transparent_white.svg
docs/_static/style.css
docs/_templates/.gitkeep
docs/_templates/layout.html
docs/imgs/orcasong_function.PNG
examples/make_data_split_config.toml
examples/orcasong_example.toml
orcasong/__init__.py
orcasong/__version__.py
orcasong/bin_edges.py
orcasong/core.py
orcasong/from_toml.py
orcasong/modules.py
orcasong/parser.py
orcasong/version.txt
orcasong.egg-info/PKG-INFO
orcasong.egg-info/SOURCES.txt
orcasong.egg-info/dependency_links.txt
orcasong.egg-info/entry_points.txt
orcasong.egg-info/requires.txt
orcasong.egg-info/top_level.txt
orcasong/extractors/__init__.py
orcasong/extractors/bundles.py
orcasong/extractors/neutrino_chain.py
orcasong/plotting/__init__.py
orcasong/plotting/binning.py
orcasong/plotting/plot_binstats.py
orcasong/tools/__init__.py
orcasong/tools/concatenate.py
orcasong/tools/make_data_split.py
orcasong/tools/postproc.py
orcasong/tools/shuffle2.py
scraps/old_orcasong/legacy/__init__.py
scraps/old_orcasong/legacy/default_config.toml
scraps/old_orcasong/legacy/file_to_hits.py
scraps/old_orcasong/legacy/geo_binning.py
scraps/old_orcasong/legacy/hits_to_histograms.py
scraps/old_orcasong/legacy/io.py
scraps/old_orcasong/legacy/make_nn_images.py
scraps/old_orcasong/legacy/utils.py
