Metadata-Version: 1.1
Name: orcasong
Version: 4.8.3
Summary: Makes images for a NN based on the hit information of neutrino events in the neutrino telescope KM3NeT
Home-page: https://git.km3net.de/ml/OrcaSong
Author: Stefan Reck, Michael Moser
Author-email: stefan.reck@fau.de, mmoser@km3net.de, michael.m.moser@fau.de
License: AGPL
Platform: UNKNOWN
Classifier: Development Status :: 3 - Alpha
Classifier: Intended Audience :: Developers
Classifier: Intended Audience :: Science/Research
Classifier: Programming Language :: Python
